flask_caster.py
Flask_Caster-0.1.0.dist-info/DESCRIPTION.rst
Flask_Caster-0.1.0.dist-info/METADATA
Flask_Caster-0.1.0.dist-info/RECORD
Flask_Caster-0.1.0.dist-info/WHEEL
Flask_Caster-0.1.0.dist-info/metadata.json
Flask_Caster-0.1.0.dist-info/top_level.txt
