Metadata-Version: 2.0
Name: Flask-Caster
Version: 0.1.0
Summary: A simple Flask extension for automatically casting the type of query arguments.
Home-page: http://github.com/kennethreitz/Flask-Caster
Author: Kenneth Reitz
Author-email: me@kennethreitz.org
License: BSD
Platform: any
Classifier: Environment :: Web Environment
Classifier: Intended Audience :: Developers
Classifier: License :: OSI Approved :: BSD License
Classifier: Operating System :: OS Independent
Classifier: Programming Language :: Python
Classifier: Topic :: Internet :: WWW/HTTP :: Dynamic Content
Classifier: Topic :: Software Development :: Libraries :: Python Modules
Requires-Dist: Flask
